control/__init__.py
control/file_operation.py
control/gpio.py
control/jiami.py
control/machine_learning.py
control/maths.py
control/shijue0.py
control/shijue1.py
control/shijue2.py
control/unique.py
control/yuyin.py
control/lcd/LCD_0inch96.py
control/lcd/LCD_1inch14.py
control/lcd/LCD_1inch28.py
control/lcd/LCD_1inch3.py
control/lcd/LCD_1inch54.py
control/lcd/LCD_1inch8.py
control/lcd/LCD_2inch.py
control/lcd/LCD_2inch4.py
control/lcd/__init__.py
control/lcd/lcdconfig.py
control/util/Voice_line_patrol.py
control/util/__init__.py
control/util/all_path.py
control/util/auto_poetry.py
control/util/checkLibVersion.py
control/util/download.py
control/util/flappy_bird.py
control/util/local_yuyin.py
control/util/ml_tool.py
control/util/number_convert.py
control/util/opencv_tool.py
control/util/playsound_change.py
control/util/word_cloud.py
control_scnu-0.8.9.dist-info/LICENSE.txt
control_scnu-0.8.9.dist-info/METADATA
control_scnu-0.8.9.dist-info/WHEEL
control_scnu-0.8.9.dist-info/top_level.txt
control_scnu-0.8.9.dist-info/RECORD
