Metadata-Version: 2.1
Name: control-scnu
Version: 0.8.9
Summary: The code package for HuaGuang AI Education
Home-page: https://github.com/pypa/sampleproject
Author: HuaGuangEdu
Author-email: huaguangcase@163.com
Classifier: Programming Language :: Python :: 3.7
Classifier: Programming Language :: Python :: 3.8
Classifier: Programming Language :: Python :: 3.9
Classifier: Programming Language :: Python :: 3.10
Classifier: Programming Language :: Python :: 3
Classifier: License :: OSI Approved :: MIT License
Classifier: Operating System :: OS Independent
Requires-Python: >=3.7, <3.11
License-File: LICENSE.txt
Requires-Dist: baidu-aip ==2.2.18.0
Requires-Dist: certifi ==2021.5.30
Requires-Dist: charset-normalizer ==2.0.6
Requires-Dist: future ==0.18.2
Requires-Dist: idna ==3.2
Requires-Dist: iso8601 ==0.1.16
Requires-Dist: joblib ==1.1.0
Requires-Dist: numpy
Requires-Dist: opencv-contrib-python ==4.5.3.56
Requires-Dist: opencv-python ==4.5.3.56
Requires-Dist: Pillow ==8.3.2
Requires-Dist: pygame
Requires-Dist: pyzbar ==0.1.8
Requires-Dist: redis ==3.5.3
Requires-Dist: requests ==2.26.0
Requires-Dist: scikit-learn ==1.0
Requires-Dist: scipy ==1.7.1
Requires-Dist: threadpoolctl ==3.0.0
Requires-Dist: urllib3 ==1.26.7
Requires-Dist: pandas
Requires-Dist: cvzone
Requires-Dist: imutils
Requires-Dist: websocket
Requires-Dist: websocket-client
Requires-Dist: protobuf ==3.19.0
Requires-Dist: pyttsx3
Requires-Dist: wordcloud
Requires-Dist: jieba
Requires-Dist: py7zr
Requires-Dist: tqdm
Requires-Dist: browser-cookie3
